datarangers/__init__.py
datarangers/collector/__init__.py
datarangers/collector/event_collector.py
datarangers/collector/config/__init__.py
datarangers/collector/config/collector_config.py
datarangers/collector/model/__init__.py
datarangers/collector/model/event.py
datarangers/collector/model/header.py
datarangers/collector/model/items.py
datarangers/collector/model/items_method.py
datarangers/collector/model/message.py
datarangers/collector/model/profile_method.py
datarangers/collector/util/__init__.py
datarangers/collector/util/constants.py
datarangers/collector/writer/__init__.py
datarangers/collector/writer/writer.py
datarangers_sdk_python-1.1.1.dist-info/METADATA
datarangers_sdk_python-1.1.1.dist-info/WHEEL
datarangers_sdk_python-1.1.1.dist-info/top_level.txt
datarangers_sdk_python-1.1.1.dist-info/RECORD
